dumbjuice/__init__.py
dumbjuice/__main__.py
dumbjuice/__version__.py
dumbjuice/build.py
dumbjuice/create_ico_entry.py
dumbjuice/utils.py
dumbjuice/assets/__init__.py
dumbjuice/assets/djicon.ico
dumbjuice/bin/__init__.py
dumbjuice/bin/nsis/COPYING
dumbjuice/bin/nsis/NSIS.chm
dumbjuice/bin/nsis/NSIS.exe
dumbjuice/bin/nsis/makensis.exe
dumbjuice/bin/nsis/makensisw.exe
dumbjuice/bin/nsis/nsisconf.nsh
dumbjuice/bin/nsis/Bin/GenPat.exe
dumbjuice/bin/nsis/Bin/MakeLangId.exe
dumbjuice/bin/nsis/Bin/RegTool-x86.bin
dumbjuice/bin/nsis/Bin/makensis.exe
dumbjuice/bin/nsis/Bin/zip2exe.exe
dumbjuice/bin/nsis/Bin/zlib1.dll
dumbjuice/bin/nsis/Contrib/Graphics/Checks/big.bmp
dumbjuice/bin/nsis/Contrib/Graphics/Checks/classic-cross.bmp
dumbjuice/bin/nsis/Contrib/Graphics/Checks/classic.bmp
dumbjuice/bin/nsis/Contrib/Graphics/Checks/colorful.bmp
dumbjuice/bin/nsis/Contrib/Graphics/Checks/grey-cross.bmp
dumbjuice/bin/nsis/Contrib/Graphics/Checks/grey.bmp
dumbjuice/bin/nsis/Contrib/Graphics/Checks/modern.bmp
dumbjuice/bin/nsis/Contrib/Graphics/Checks/red-round.bmp
dumbjuice/bin/nsis/Contrib/Graphics/Checks/red.bmp
dumbjuice/bin/nsis/Contrib/Graphics/Checks/simple-round.bmp
dumbjuice/bin/nsis/Contrib/Graphics/Checks/simple-round2.bmp
dumbjuice/bin/nsis/Contrib/Graphics/Checks/simple.bmp
dumbjuice/bin/nsis/Contrib/Graphics/Header/nsis-r.bmp
dumbjuice/bin/nsis/Contrib/Graphics/Header/nsis.bmp
dumbjuice/bin/nsis/Contrib/Graphics/Header/nsis3-branding-r.bmp
dumbjuice/bin/nsis/Contrib/Graphics/Header/nsis3-branding.bmp
dumbjuice/bin/nsis/Contrib/Graphics/Header/nsis3-grey-right.bmp
dumbjuice/bin/nsis/Contrib/Graphics/Header/nsis3-grey.bmp
dumbjuice/bin/nsis/Contrib/Graphics/Header/nsis3-metro-right.bmp
dumbjuice/bin/nsis/Contrib/Graphics/Header/nsis3-metro.bmp
dumbjuice/bin/nsis/Contrib/Graphics/Header/nsis3-vintage-right.bmp
dumbjuice/bin/nsis/Contrib/Graphics/Header/nsis3-vintage.bmp
dumbjuice/bin/nsis/Contrib/Graphics/Header/orange-nsis.bmp
dumbjuice-0.9.3.dist-info/licenses/LICENSE
dumbjuice-0.9.3.dist-info/METADATA
dumbjuice-0.9.3.dist-info/WHEEL
dumbjuice-0.9.3.dist-info/entry_points.txt
dumbjuice-0.9.3.dist-info/top_level.txt
dumbjuice-0.9.3.dist-info/RECORD
