Metadata-Version: 2.4
Name: dumbjuice
Version: 0.9.3
Summary: DumbJuice is a Python module that simplifies the process of packaging small Python programs into self-contained installable packages. These packages can be shared with non-technical users, who only need to run a single install.bat file to install Python, set up a virtual environment, install necessary dependencies, and create a shortcut to the program on their desktop.
Home-page: https://github.com/lorithai/dumbjuice
Author: Lorithai
Author-email: lorithai@gmail.com
Classifier: Programming Language :: Python :: 3
Classifier: License :: OSI Approved :: MIT License
Classifier: Operating System :: OS Independent
Requires-Python: >=3.6
License-File: LICENSE
Requires-Dist: pillow==11.3.0
Requires-Dist: requests
Requires-Dist: beautifulsoup4==4.13.5
Requires-Dist: packaging
Dynamic: author
Dynamic: author-email
Dynamic: classifier
Dynamic: description
Dynamic: description-content-type
Dynamic: home-page
Dynamic: license-file
Dynamic: requires-dist
Dynamic: requires-python
Dynamic: summary
